{
  "slug": "entretenir-sol-epoxy-erreurs-eviter",
  "title": "Comment entretenir un sol époxy : 7 erreurs à éviter",
  "category": "Conseils",
  "date": "2026-04-11",
  "image": "entrepot2.webp",
  "readTime": "4 min",
  "content": "<p>Un sol époxy bien entretenu peut durer plus de 20 ans. Mais certaines erreurs courantes peuvent réduire sa durée de vie. Voici les pièges à éviter pour garder votre sol impeccable.</p><h2>Erreur 1 : Utiliser des produits abrasifs</h2><p>Les nettoyants à base de javel concentrée ou les poudres abrasives peuvent rayer et ternir la surface. Privilégiez un nettoyant neutre dilué dans de l'eau tiède.</p><h2>Erreur 2 : Négliger le nettoyage régulier</h2><p>Même si le sol époxy est résistant, le sable et les petits cailloux agissent comme du papier de verre sous les semelles. Un balayage régulier prévient les micro-rayures.</p><h2>Erreur 3 : Laisser stagner les liquides</h2><p>L'époxy est imperméable, mais laisser un liquide stagner pendant des jours peut créer des auréoles. Essuyez les flaques rapidement, surtout dans le garage.</p><h2>Erreur 4 : Traîner des objets lourds</h2><p>Déplacer des meubles ou équipements lourds sans protection peut rayer le sol. Utilisez des patins en feutre sous les pieds de meubles et soulevez plutôt que de traîner.</p><h2>Erreur 5 : Ignorer les petites réparations</h2><p>Un éclat ou une fissure, même minime, peut s'agrandir avec le temps. Une retouche rapide coûte peu et évite une réfection complète.</p><h2>Erreur 6 : Utiliser un nettoyeur haute pression</h2><p>Le jet haute pression peut endommager la finition UV et décoller les bords. Un balai-brosse et une serpillière sont amplement suffisants.</p><h2>Erreur 7 : Appliquer de la cire</h2><p>Contrairement au parquet, le sol époxy n'a pas besoin de cire. En ajouter crée une couche glissante qui jaunit avec le temps.</p><h2>L'entretien idéal en résumé</h2><p>Un balayage hebdomadaire et un coup de serpillière humide avec un savon neutre — c'est tout ce qu'il faut. Simple, rapide, efficace.</p>"
}