{
  "slug": "transformation-showroom-paris-epoxy-metallique",
  "title": "Transformation d'un showroom à Paris : l'effet métallique époxy",
  "category": "Inspirations",
  "date": "2026-04-09",
  "image": "shoowroom2.webp",
  "readTime": "3 min",
  "content": "<p>Quand une boutique haut de gamme à Paris nous a contactés pour transformer son showroom de 120 m², le défi était clair : créer un sol qui soit une véritable signature visuelle.</p><h2>Le projet</h2><p>Le client souhaitait un sol qui reflète le positionnement premium de sa marque. Après analyse de l'espace et de la lumière naturelle, nous avons proposé un <strong>époxy effet métallique bleu miroir</strong> — un rendu spectaculaire qui change selon l'angle de vue.</p><h2>Les étapes de la transformation</h2><p>Le chantier s'est déroulé en 3 jours :</p><ul><li><strong>Jour 1</strong> : Ponçage diamant du béton existant et aspiration industrielle pour préparer le support</li><li><strong>Jour 2</strong> : Application du primaire Chemtec haute adhérence, puis de la résine époxy avec pigments métalliques</li><li><strong>Jour 3</strong> : Vernis de protection UV finition brillante pour un effet miroir durable</li></ul><h2>Le résultat</h2><p>Le sol crée des reflets profonds qui captent la lumière des spots du showroom. Les clients du magasin remarquent immédiatement le sol en entrant — mission accomplie pour renforcer l'image de marque.</p><h2>Chiffres clés</h2><ul><li><strong>Surface</strong> : 120 m²</li><li><strong>Durée</strong> : 3 jours</li><li><strong>Finition</strong> : Métallique bleu miroir</li><li><strong>Garantie</strong> : 10 ans</li></ul><p>Vous avez un projet similaire ? <strong>Contactez-nous</strong> pour un devis gratuit personnalisé.</p>"
}